transformers/__init__.py
transformers/activations.py
transformers/activations_tf.py
transformers/audio_utils.py
transformers/configuration_utils.py
transformers/convert_graph_to_onnx.py
transformers/convert_pytorch_checkpoint_to_tf2.py
transformers/convert_slow_tokenizer.py
transformers/convert_slow_tokenizers_checkpoints_to_fast.py
transformers/convert_tf_hub_seq_to_seq_bert_to_pytorch.py
transformers/debug_utils.py
transformers/deepspeed.py
transformers/dependency_versions_check.py
transformers/dependency_versions_table.py
transformers/dynamic_module_utils.py
transformers/feature_extraction_sequence_utils.py
transformers/feature_extraction_utils.py
transformers/file_utils.py
transformers/generation_flax_utils.py
transformers/generation_tf_utils.py
transformers/generation_utils.py
transformers/hf_argparser.py
transformers/hyperparameter_search.py
transformers/image_processing_utils.py
transformers/image_transforms.py
transformers/image_utils.py
transformers/keras_callbacks.py
transformers/modelcard.py
transformers/modeling_flax_outputs.py
transformers/modeling_flax_pytorch_utils.py
transformers/modeling_flax_utils.py
transformers/modeling_outputs.py
transformers/modeling_tf_outputs.py
transformers/modeling_tf_pytorch_utils.py
transformers/modeling_tf_utils.py
transformers/modeling_utils.py
transformers/optimization.py
transformers/optimization_tf.py
transformers/processing_utils.py
transformers/pytorch_utils.py
transformers/testing_utils.py
transformers/tf_utils.py
transformers/time_series_utils.py
transformers/tokenization_utils.py
transformers/tokenization_utils_base.py
transformers/tokenization_utils_fast.py
transformers/trainer.py
transformers/trainer_callback.py
transformers/trainer_pt_utils.py
transformers/trainer_seq2seq.py
transformers/trainer_tf.py
transformers/trainer_utils.py
transformers/training_args.py
transformers/training_args_seq2seq.py
transformers/training_args_tf.py
transformers/version.py
transformers/benchmark/__init__.py
nm_transformers-1.7.0.43401.dist-info/LICENSE
nm_transformers-1.7.0.43401.dist-info/METADATA
nm_transformers-1.7.0.43401.dist-info/WHEEL
nm_transformers-1.7.0.43401.dist-info/entry_points.txt
nm_transformers-1.7.0.43401.dist-info/top_level.txt
nm_transformers-1.7.0.43401.dist-info/RECORD
